deep_ner/__init__.py
deep_ner/bert_ner.py
deep_ner/dataset_splitting.py
deep_ner/elmo_ner.py
deep_ner/quality.py
deep_ner/udpipe_data.py
deep_ner/utils.py
deep_ner-0.0.6.dist-info/LICENSE
deep_ner-0.0.6.dist-info/METADATA
deep_ner-0.0.6.dist-info/WHEEL
deep_ner-0.0.6.dist-info/top_level.txt
deep_ner-0.0.6.dist-info/RECORD
