Metadata-Version: 2.1
Name: deep-ner
Version: 0.0.6
Summary: Deep-NER: named entity recognizer based on ELMo or BERT as embeddings and CRF as final classifier
Home-page: https://github.com/bond005/deep_ner
Author: Ivan Bondarenko
Author-email: bond005@yandex.ru
License: Apache License Version 2.0
Keywords: elmo,bert,ner,crf,nlp,tensorflow,scikit-learn
Platform: UNKNOWN
Classifier: Development Status :: 3 - Alpha
Classifier: Intended Audience :: Science/Research
Classifier: Intended Audience :: Developers
Classifier: Topic :: Software Development
Classifier: Topic :: Scientific/Engineering
Classifier: Topic :: Scientific/Engineering :: Artificial Intelligence
Classifier: Topic :: Text Processing
Classifier: Topic :: Text Processing :: Linguistic
Classifier: License :: OSI Approved :: Apache Software License
Classifier: Programming Language :: Python :: 3.6
Classifier: Programming Language :: Python :: 3.7
Requires-Dist: nltk (==3.4.5)
Requires-Dist: numpy (==1.18.1)
Requires-Dist: scikit-learn (==0.22.1)
Requires-Dist: scipy (==1.4.1)
Requires-Dist: tensorboard (==1.15.0)
Requires-Dist: tensorflow (==1.15.0)
Requires-Dist: tensorflow-hub (==0.8.0)
Requires-Dist: bert-tensorflow (==1.0.1)
Requires-Dist: spacy-udpipe (==0.2.0)
Requires-Dist: spacy (==2.2.3)
Requires-Dist: pymorphy2 (==0.8)
Requires-Dist: rusenttokenize (==0.0.5)
